autonym/__init__.py
autonym/autonym.py
autonym-0.1.0.dist-info/METADATA
autonym-0.1.0.dist-info/WHEEL
autonym-0.1.0.dist-info/RECORD
