Metadata-Version: 2.4
Name: autonym
Version: 0.1.0
Summary: Automated ML run naming and summarization using local or remote LLMs.
Author-email: Leello Tadesse Dadi <leello.tadesse@gmail.com>
License: MIT
Requires-Python: >=3.10
Requires-Dist: ollama>=0.6.1
Requires-Dist: openai>=2.14.0
Requires-Dist: pydantic>=2.12.5
